{
    "cordova-plugin-whitelist": {
        "source": {
            "type": "registry",
            "id": "cordova-plugin-whitelist"
        },
        "is_top_level": true,
        "variables": {}
    },
    "cordova-plugin-customurlscheme": {
        "source": {
            "type": "registry",
            "id": "cordova-plugin-customurlscheme"
        },
        "is_top_level": true,
        "variables": {
            "URL_SCHEME": "sevencentre"
        }
    },
    "phonegap-facebook-plugin": {
        "source": {
            "type": "local",
            "path": "phonegap-facebook-plugin-master"
        },
        "is_top_level": true,
        "variables": {
            "APP_ID": "440773049460625",
            "APP_NAME": "Sevens Cards Game"
        }
    }
}